AUTHORS
CHANGELOG.md
LICENSE
MANIFEST.in
README.md
setup.py
django_imgix/__init__.py
django_imgix/models.py
django_imgix.egg-info/PKG-INFO
django_imgix.egg-info/SOURCES.txt
django_imgix.egg-info/dependency_links.txt
django_imgix.egg-info/requires.txt
django_imgix.egg-info/top_level.txt
django_imgix/templatetags/__init__.py
django_imgix/templatetags/imgix_tags.py
django_imgix/tests/__init__.py
django_imgix/tests/settings.py
django_imgix/tests/tests.py